chatushka/__init__.py
chatushka/__main__.py
chatushka/__version__.py
chatushka/bot/__init__.py
chatushka/bot/data/eight_ball.yaml
chatushka/bot/data/lukashenko.txt
chatushka/bot/internal/__init__.py
chatushka/bot/internal/data_dir.py
chatushka/bot/internal/mute.py
chatushka/bot/main.py
chatushka/bot/matchers/__init__.py
chatushka/bot/matchers/admin/__init__.py
chatushka/bot/matchers/admin/mute.py
chatushka/bot/matchers/admin/pin.py
chatushka/bot/matchers/bobuk_jokes.py
chatushka/bot/matchers/eight_ball.py
chatushka/bot/matchers/helpers.py
chatushka/bot/matchers/lukashenko.py
chatushka/bot/matchers/philosophy.py
chatushka/bot/matchers/suicide.py
chatushka/bot/matchers/welcoming.py
chatushka/bot/models/__init__.py
chatushka/bot/settings.py
chatushka/core/__init__.py
chatushka/core/bot.py
chatushka/core/matchers/__init__.py
chatushka/core/matchers/base.py
chatushka/core/matchers/chat_users_movements.py
chatushka/core/matchers/commands.py
chatushka/core/matchers/cron.py
chatushka/core/matchers/events.py
chatushka/core/matchers/regex.py
chatushka/core/models.py
chatushka/core/protocols.py
chatushka/core/services/__init__.py
chatushka/core/services/base.py
chatushka/core/services/mongodb/__init__.py
chatushka/core/services/mongodb/settings.py
chatushka/core/services/mongodb/utils.py
chatushka/core/services/mongodb/wrapper.py
chatushka/core/transports/__init__.py
chatushka/core/transports/models.py
chatushka/core/transports/telegram_bot_api.py
chatushka/core/transports/utils.py
chatushka/core/utils.py
chatushka/webui/__init__.py
chatushka/webui/routes/__init__.py
chatushka-0.10.1.dist-info/WHEEL
chatushka-0.10.1.dist-info/METADATA
chatushka-0.10.1.dist-info/RECORD
