Metadata-Version: 2.1
Name: chatushka
Version: 0.10.1
Summary: Bot that can make your chat explode!
Home-page: https://github.com/shpaker/chatushka
Author: Aleksandr Shpak
Author-email: shpaker@gmail.com
Requires-Python: >=3.9,<4.0
Classifier: Programming Language :: Python :: 3
Classifier: Programming Language :: Python :: 3.10
Classifier: Programming Language :: Python :: 3.9
Requires-Dist: PyYAML (>=6.0,<7.0)
Requires-Dist: aiocron (>=1.6,<2.0)
Requires-Dist: click (>=8.0.1,<9.0.0)
Requires-Dist: httpx (>=0.22.0,<0.23.0)
Requires-Dist: motor (>=2.5.0,<3.0.0)
Requires-Dist: pydantic[dotenv] (>=1.8.2,<2.0.0)
Project-URL: Repository, https://github.com/shpaker/chatushka
